JobTitleTransformer/__init__.py
JobTitleTransformer/runner.py
JobTitleTransformer/job_scripts/ARNP.py
JobTitleTransformer/job_scripts/Acupuncturist.py
JobTitleTransformer/job_scripts/AestheticAntiAgingPhy.py
JobTitleTransformer/job_scripts/AestheticPhysician.py
JobTitleTransformer/job_scripts/AestheticPlasticSurgeon.py
JobTitleTransformer/job_scripts/AlternativeMedicinePhysician.py
JobTitleTransformer/job_scripts/Anaesthesist.py
JobTitleTransformer/job_scripts/Anatomist.py
JobTitleTransformer/job_scripts/Andrologist.py
JobTitleTransformer/job_scripts/AngiologistPhlebologist.py
JobTitleTransformer/job_scripts/AntiagingPhysician.py
JobTitleTransformer/job_scripts/BiologistBiochemist.py
JobTitleTransformer/job_scripts/BiomedicalPhysician.py
JobTitleTransformer/job_scripts/Cardiologist.py
JobTitleTransformer/job_scripts/ClinicManager.py
JobTitleTransformer/job_scripts/ClinicalStaff.py
JobTitleTransformer/job_scripts/CompanyCEO.py
JobTitleTransformer/job_scripts/CompanyManager.py
JobTitleTransformer/job_scripts/CompanyMedicalStaff.py
JobTitleTransformer/job_scripts/CompanyRepresentative.py
JobTitleTransformer/job_scripts/Consultant.py
JobTitleTransformer/job_scripts/CosmeticDermCosmeticSurgeon.py
JobTitleTransformer/job_scripts/CosmetologistMD.py
JobTitleTransformer/job_scripts/Cytologist.py
JobTitleTransformer/job_scripts/DentalAssistant.py
JobTitleTransformer/job_scripts/DentalSurgeon.py
JobTitleTransformer/job_scripts/Dentist.py
JobTitleTransformer/job_scripts/DermatologicSurgeon.py
JobTitleTransformer/job_scripts/Dermatologist.py
JobTitleTransformer/job_scripts/Distributor.py
JobTitleTransformer/job_scripts/ENTPhysician.py
JobTitleTransformer/job_scripts/Employee.py
JobTitleTransformer/job_scripts/Endocrinologist.py
JobTitleTransformer/job_scripts/Esthetician.py
JobTitleTransformer/job_scripts/EventManager.py
JobTitleTransformer/job_scripts/FacialPlasticSurgeon.py
JobTitleTransformer/job_scripts/GeneralPhysician.py
JobTitleTransformer/job_scripts/GeneralSurgeon.py
JobTitleTransformer-0.1.20.dist-info/LICENSE
JobTitleTransformer-0.1.20.dist-info/METADATA
JobTitleTransformer-0.1.20.dist-info/WHEEL
JobTitleTransformer-0.1.20.dist-info/entry_points.txt
JobTitleTransformer-0.1.20.dist-info/top_level.txt
JobTitleTransformer-0.1.20.dist-info/RECORD
