Metadata-Version: 2.1
Name: JobTitleTransformer
Version: 0.1.20
Summary: A healthcare-focused job title transformation pipeline.
Home-page: https://github.com/PrasannaDataBus/JobTitleTransformer
Author: Prasanna UTHAMARAJ
Author-email: prasanna.uthamaraj@informa.com
License: MIT
Platform: UNKNOWN
Classifier: Programming Language :: Python :: 3
Classifier: Operating System :: OS Independent
Classifier: Intended Audience :: Developers
Classifier: License :: OSI Approved :: MIT License
Requires-Python: >=3.7
License-File: LICENSE
Requires-Dist: pandas
Requires-Dist: numpy
Requires-Dist: nltk
Requires-Dist: termcolor
Requires-Dist: tabulate
Requires-Dist: scikit-learn
Requires-Dist: sentence-transformers
Requires-Dist: faiss-cpu
Requires-Dist: torch
